KeyFrameDetector/__init__.py
KeyFrameDetector/key_frame_detector.py
KeyFrameDetector/utils.py
video_keyframe_detector-0.1.0.dist-info/licenses/LICENSE
video_keyframe_detector-0.1.0.dist-info/METADATA
video_keyframe_detector-0.1.0.dist-info/WHEEL
video_keyframe_detector-0.1.0.dist-info/entry_points.txt
video_keyframe_detector-0.1.0.dist-info/top_level.txt
video_keyframe_detector-0.1.0.dist-info/RECORD
