Metadata-Version: 2.4
Name: video-keyframe-detector
Version: 0.1.0
Summary: It is a simple python tool to extract key-frames from a video
Home-page: https://github.com/joelibaceta/video-keyframe-extractor
Author: Joel Ibaceta
Author-email: Joel Ibaceta <mail@joelibaceta.com>
License: GPL-3.0-or-later
Project-URL: Homepage, https://github.com/joelibaceta/video-keyframe-detector
Requires-Python: >=3.7
License-File: LICENSE
Requires-Dist: numpy
Requires-Dist: opencv-python
Requires-Dist: peakutils
Dynamic: author
Dynamic: home-page
Dynamic: license-file
